warpq/__init__.py
warpq/core.py
warpq/utils.py
warpq-1.5.2.dist-info/LICENSE.txt
warpq-1.5.2.dist-info/METADATA
warpq-1.5.2.dist-info/WHEEL
warpq-1.5.2.dist-info/top_level.txt
warpq-1.5.2.dist-info/RECORD
