Metadata-Version: 2.1
Name: warpq
Version: 1.5.2
Summary: WARP-Q: Quality Prediction For Generative Neural Speech Codecs
Home-page: https://github.com/wjassim/WARP-Q
Author: Wissam A Jassim
Author-email: wissam.a.jassim@gmail.com
Classifier: Programming Language :: Python :: 3
Classifier: License :: OSI Approved :: Apache Software License
Classifier: Operating System :: OS Independent
Requires-Python: >=3.8
License-File: LICENSE.txt
Requires-Dist: librosa
Requires-Dist: pandas
Requires-Dist: seaborn
Requires-Dist: scipy
Requires-Dist: tqdm
Requires-Dist: pyvad
Requires-Dist: numpy
Requires-Dist: joblib
Requires-Dist: matplotlib
